plover_run_shell.py
plover_run_shell-0.0.4.dist-info/LICENSE
plover_run_shell-0.0.4.dist-info/METADATA
plover_run_shell-0.0.4.dist-info/WHEEL
plover_run_shell-0.0.4.dist-info/entry_points.txt
plover_run_shell-0.0.4.dist-info/top_level.txt
plover_run_shell-0.0.4.dist-info/zip-safe
plover_run_shell-0.0.4.dist-info/RECORD
