Metadata-Version: 2.1
Name: plover-run-shell
Version: 0.0.4
Summary: Command plugin for Plover to run an arbitrary shell command
Home-page: https://github.com/user202729/plover_run_shell
Author: user202729
License: GNU General Public License v3 or later (GPLv3+)
Keywords: plover plover_plugin
Platform: UNKNOWN
Classifier: Environment :: Plugins
Classifier: License :: OSI Approved :: GNU General Public License v3 or later (GPLv3+)
Classifier: Operating System :: OS Independent
Classifier: Programming Language :: Python :: 3
Requires-Dist: plover (>=4.0.0.dev8)
